anchorestigruntime/__init__.py
anchorestigruntime/inputs.py
anchorestigruntime/main.py
anchorestigruntime/provision.py
anchorestigruntime/runtime.py
anchorestigruntime/train-k8s-container/CHANGELOG.md
anchorestigruntime/train-k8s-container/Gemfile
anchorestigruntime/train-k8s-container/LICENSE
anchorestigruntime/train-k8s-container/README.md
anchorestigruntime/train-k8s-container/Rakefile
anchorestigruntime/train-k8s-container/VERSION
anchorestigruntime/train-k8s-container/sonar-project.properties
anchorestigruntime/train-k8s-container/train-k8s-container.gemspec
anchorestigruntime/train-k8s-container/.expeditor/config.yml
anchorestigruntime/train-k8s-container/.expeditor/coverage.pipeline.yml
anchorestigruntime/train-k8s-container/.expeditor/update_version.sh
anchorestigruntime/train-k8s-container/.expeditor/verify.pipeline.yml
anchorestigruntime/train-k8s-container/.expeditor/buildkite/coverage.sh
anchorestigruntime/train-k8s-container/.expeditor/buildkite/run_linux_tests.sh
anchorestigruntime/train-k8s-container/docs/README.md
anchorestigruntime/train-k8s-container/lib/train-k8s-container.rb
anchorestigruntime/train-k8s-container/lib/train/k8s/container/connection.rb
anchorestigruntime/train-k8s-container/lib/train/k8s/container/kubectl_exec_client.rb
anchorestigruntime/train-k8s-container/lib/train/k8s/container/platform.rb
anchorestigruntime/train-k8s-container/lib/train/k8s/container/transport.rb
anchorestigruntime/train-k8s-container/lib/train/k8s/container/version.rb
anchorestigruntime/train-k8s-container/spec/spec_helper.rb
anchorestigruntime/train-k8s-container/spec/train/k8s/container_spec.rb
anchorestigruntime/train-k8s-container/spec/train/k8s/kubectl_exec_client_spec.rb
anchorestigruntime/train-k8s-container/spec/train/k8s/container/connection_spec.rb
anchorestigruntime/train-k8s-container/spec/train/k8s/container/platform_spec.rb
anchorestigruntime/train-k8s-container/spec/train/k8s/container/transport_spec.rb
anchorestig_runtime-0.75.1.dist-info/LICENSE
anchorestig_runtime-0.75.1.dist-info/METADATA
anchorestig_runtime-0.75.1.dist-info/WHEEL
anchorestig_runtime-0.75.1.dist-info/entry_points.txt
anchorestig_runtime-0.75.1.dist-info/top_level.txt
anchorestig_runtime-0.75.1.dist-info/RECORD
