Metadata-Version: 2.1
Name: anchorestig-runtime
Version: 0.75.1
Summary: A tool for performing runtime analysis using STIGs
Author: Anchore Inc.
Classifier: Programming Language :: Python :: 3
Classifier: License :: OSI Approved :: MIT License
Classifier: Operating System :: OS Independent
Requires-Python: >=3.6
License-File: LICENSE
Requires-Dist: click
Requires-Dist: boto3
